check_shapes/__init__.py
check_shapes/accessors.py
check_shapes/argument_ref.py
check_shapes/base_types.py
check_shapes/bool_specs.py
check_shapes/check_shapes.lark
check_shapes/checker.py
check_shapes/checker_context.py
check_shapes/config.py
check_shapes/decorator.py
check_shapes/docstring.lark
check_shapes/error_contexts.py
check_shapes/exceptions.py
check_shapes/inheritance.py
check_shapes/integration/__init__.py
check_shapes/integration/tf.py
check_shapes/integration/tfp.py
check_shapes/integration/torch.py
check_shapes/parser.py
check_shapes/py.typed
check_shapes/shapes.py
check_shapes/specs.py
check_shapes-1.1.1.dist-info/LICENSE
check_shapes-1.1.1.dist-info/METADATA
check_shapes-1.1.1.dist-info/WHEEL
check_shapes-1.1.1.dist-info/RECORD
